{
  "Address": "0x14094949152eddbfcd073717200da82fed8dc960",
  "Labels": {
    "bzx": {
      "Name Tag": "bZx SAI iToken",
      "Description": "bZx is a financial primitive for shorting, leverage, borrowing, and lending that empowers decentralized, efficient blockchain applications.",
      "Subcategory": "Others",
      "Token Name": "Fulcrum SAI iToken (iSAI)"
    },
    "defi": {
      "Token Name": "Fulcrum SAI iToken (iSAI)",
      "Description": "List of decentralized finance products.",
      "Subcategory": "Others"
    }
  }
}