{
  "Address": "0x24f529fd94a63E1Fdf25D77C949f05ac6Bf1B818",
  "Labels": {
    "staking": {
      "Token Name": "FIB (FIB)",
      "Description": "The process of holding funds in a cryptocurrency wallet to support the operations of a network."
    },
    "website-down": {
      "Name Tag": "FIB.DEV: FIB Token",
      "Description": "The last checked status of a website.\nPlease contact us (1. General Inquiry) if the website is back online.",
      "Token Name": "FIB (FIB)"
    },
    "yield-farming": {
      "Token Name": "FIB (FIB)"
    }
  }
}