{
  "Address": "0x27ad8e47c48063b209fa5ca14c8c46ece49b82d2",
  "Labels": {
    "gambling": {
      "Token Name": "Active World Rewards Token (AWRT)",
      "Description": "The wagering of Ethers or something of value on an event with an uncertain outcome with the primary intent of winning more Ethers or material goods."
    },
    "gaming": {
      "Token Name": "Active World Rewards Token (AWRT)",
      "Description": "The category relating to the playing of electronic games."
    },
    "metaverse": {
      "Token Name": "Active World Rewards Token (AWRT)",
      "Description": "A virtual-reality space in which users can interact with a computer-generated environment and other users."
    }
  }
}