{
  "Address": "0x2ae965cd3d2b6d186e87d9586fc3bdbfc667cacc",
  "Labels": {
    "human-resource": {
      "Token Name": "GJC (GJC)",
      "Description": "Human resources are the workforce within an organization and its the department responsible for the management of employees."
    },
    "platform": {
      "Token Name": "GJC (GJC)",
      "Description": "The technology of computer systems that defines how a system is operated as a foundation, upon which other processes, application or technologies are developed."
    }
  }
}