{
  "Address": "0x2F6Ad7743924B1901a0771746152dde44C5F11DE",
  "Labels": {
    "charity": {
      "Token Name": "SCARDust (SCARD)",
      "Description": "An organization that raises money to help people in need."
    },
    "gaming": {
      "Token Name": "SCARDust (SCARD)",
      "Description": "The category relating to the playing of electronic games."
    },
    "play-to-earn": {
      "Token Name": "SCARDust (SCARD)",
      "Description": "Players earn in-game tokens as rewards when playing the game."
    }
  }
}