{
  "Address": "0x5C406D99E04B8494dc253FCc52943Ef82bcA7D75",
  "Labels": {
    "payments": {
      "Token Name": "cUSD Currency (cUSD)",
      "Description": "Cryptocurrency payment platforms that accept their own native tokens and/or other cryptocurrencies as a form of payment."
    },
    "website-down": {
      "Name Tag": "cUSD Currency: cUSD Token",
      "Description": "The last checked status of a website.\nPlease contact us (1. General Inquiry) if the website is back online.",
      "Token Name": "cUSD Currency (cUSD)"
    }
  }
}