{
  "Address": "0x5c6ee304399dbdb9c8ef030ab642b10820db8f56",
  "Labels": {
    "balancer": {
      "Name Tag": "Balancer: B-80BAL-20WETH Token",
      "Description": "Balancer is a non-custodial portfolio manager, liquidity provider, and price sensor.",
      "Subcategory": "Others",
      "Token Name": "Balancer 80 BAL 20 WETH (B-80BAL-20WETH)"
    },
    "defi": {
      "Token Name": "Balancer 80 BAL 20 WETH (B-80BAL-20WETH)",
      "Description": "List of decentralized finance products.",
      "Subcategory": "Others"
    },
    "dex": {
      "Token Name": "Balancer 80 BAL 20 WETH (B-80BAL-20WETH)",
      "Description": "A decentralized exchange (also known as a DEX) is an exchange market that does not rely on a 3rd party service to hold the client funds but instead trades occur directly between users (peer to peer) through an automated process."
    }
  }
}