{
  "Address": "0x629a673a8242c2ac4b7b8c5d8735fbeac21a6205",
  "Labels": {
    "gaming": {
      "Name Tag": "Sorare: SOR Token",
      "Description": "The category relating to the playing of electronic games.",
      "Token Name": "Sorare (SOR)"
    },
    "sorare": {
      "Name Tag": "Sorare: SOR Token",
      "Description": "Sorare is a global fantasy football game where you can collect limited edition collectibles, manage your teams and compete to earn prizes.",
      "Token Name": "Sorare (SOR)"
    }
  }
}