{
  "Address": "0x91dfa9d9e062a50d2f351bfba0d35a9604993dac",
  "Labels": {
    "huobi": {
      "Name Tag": "Huobi: Old Address 12",
      "Description": "Huobi is one of the world’s largest digital asset trading and management service providers.\nThe Huobi service offers a wider variety of token options and giveaways to American audiences, with 24/7 personal customer support, and unparalleled security."
    },
    "old-contract": {
      "Name Tag": "Huobi: Old Address 12",
      "Description": "Contracts/addresses which are migrating or have migrated to a new contract/address. This includes token swaps as well.",
      "Subcategory": "Others"
    }
  }
}