{
  "Address": "0xf3d58d1794f2634d6649a978f2dc093898feebc0",
  "Labels": {
    "metis-andromeda": {
      "Name Tag": "Metis Andromeda: MVM L2 Chain Manager",
      "Description": "Metis Andromeda is building an easy-to-use, highly scalable, low-cost, and fully functional Layer 2 framework (Metis Rollup) to fully support the application and business migration from Web 2.0 to Web 3.0. Its scalable protocol supports a wide range of use cases, including yield farming, DEX trading, and powering the gig economy via dApps that offer cheap and fast micropayments."
    }
  }
}