{
  "Address": "0xf4b5470523ccd314c6b9da041076e7d79e0df267",
  "Labels": {
    "artificial-intelligence": {
      "Token Name": "BlockBank (BBANK)",
      "Description": "Artificial intelligence refers to the development of a computer program to accurately interpret and learn external data with the goal of achieving specific objectives through adaptable program learning."
    },
    "banking": {
      "Token Name": "BlockBank (BBANK)"
    },
    "defi": {
      "Token Name": "BlockBank (BBANK)",
      "Description": "List of decentralized finance products.",
      "Subcategory": "Others"
    }
  }
}